{
  "navigationStyle":"custom",
  "usingComponents": {
    "van-search": "@vant/weapp/search/index",
    "van-cell": "@vant/weapp/cell/index",
    "van-button": "@vant/weapp/button/index",
    "van-icon": "@vant/weapp/icon/index",
    "van-sidebar": "@vant/weapp/sidebar/index",
    "van-sidebar-item": "@vant/weapp/sidebar-item/index",
    "van-index-bar": "@vant/weapp/index-bar/index",
    "van-index-anchor": "@vant/weapp/index-anchor/index",
    "van-card": "@vant/weapp/card/index",
    "goods-item": "../../components/goods-item/goodItem",
    "shopCart-item": "../../components/shopCartItem/shopCartItem",
    "van-popup": "@vant/weapp/popup/index",
    "van-submit-bar": "@vant/weapp/submit-bar/index",
    "van-image": "@vant/weapp/image/index"
  }
}